drvi/__init__.py
drvi/model/__init__.py
drvi/nn_modules/__init__.py
drvi/nn_modules/embedding.py
drvi/nn_modules/encodig.py
drvi/nn_modules/freezable.py
drvi/nn_modules/gradients.py
drvi/nn_modules/noise_model.py
drvi/nn_modules/prior.py
drvi/nn_modules/layer/__init__.py
drvi/nn_modules/layer/factory.py
drvi/nn_modules/layer/linear_layer.py
drvi/nn_modules/layer/structures.py
drvi/scvi_tools_based/__init__.py
drvi/scvi_tools_based/data/__init__.py
drvi/scvi_tools_based/data/fields/__init__.py
drvi/scvi_tools_based/data/fields/_fixed_fields.py
drvi/scvi_tools_based/model/__init__.py
drvi/scvi_tools_based/model/_drvi.py
drvi/scvi_tools_based/model/base/__init__.py
drvi/scvi_tools_based/model/base/_archesmixin.py
drvi/scvi_tools_based/model/base/_generative_mixin.py
drvi/scvi_tools_based/module/__init__.py
drvi/scvi_tools_based/module/_constants.py
drvi/scvi_tools_based/module/_drvi.py
drvi/scvi_tools_based/nn/__init__.py
drvi/scvi_tools_based/nn/_base_components.py
drvi/utils/__init__.py
drvi/utils/metrics/__init__.py
drvi/utils/metrics/_aggregation.py
drvi/utils/metrics/_benchmark.py
drvi/utils/metrics/_pairwise.py
drvi/utils/misc/__init__.py
drvi/utils/misc/_hvg.py
drvi/utils/plotting/__init__.py
drvi/utils/plotting/_cmap.py
drvi/utils/plotting/_interpretability.py
drvi/utils/plotting/_latent.py
drvi/utils/tools/__init__.py
drvi/utils/tools/_latent.py
drvi/utils/tools/interpretability/__init__.py
drvi/utils/tools/interpretability/_differential_vars.py
drvi/utils/tools/interpretability/_latent_traverse.py
drvi_py-0.2.1.dist-info/METADATA
drvi_py-0.2.1.dist-info/WHEEL
drvi_py-0.2.1.dist-info/licenses/LICENSE
drvi_py-0.2.1.dist-info/RECORD
