Metadata-Version: 2.4
Name: drvi-py
Version: 0.2.1
Summary: Unsupervised Deep Disentangled Representation of Single-Cell Omics
Project-URL: Documentation, https://drvi.readthedocs.io/
Project-URL: Homepage, https://github.com/theislab/drvi
Project-URL: Source, https://github.com/theislab/drvi
Author: Amir Ali Moinfar
Maintainer-email: Amir Ali Moinfar <moinfar.amirali@gmail.com>
License: BSD 3-Clause License
License-File: LICENSE
Classifier: Intended Audience :: Developers
Classifier: Intended Audience :: Science/Research
Classifier: License :: OSI Approved :: BSD License
Classifier: Natural Language :: English
Classifier: Operating System :: MacOS :: MacOS X
Classifier: Operating System :: POSIX :: Linux
Classifier: Programming Language :: Python :: 3 :: Only
Classifier: Programming Language :: Python :: 3.10
Classifier: Programming Language :: Python :: 3.11
Classifier: Programming Language :: Python :: 3.12
Classifier: Programming Language :: Python :: 3.13
Classifier: Programming Language :: Python :: 3.14
Classifier: Topic :: Scientific/Engineering :: Artificial Intelligence
Classifier: Topic :: Scientific/Engineering :: Bio-Informatics
Requires-Python: <3.15,>=3.10
Requires-Dist: anndata<0.13,>=0.10.2
Requires-Dist: lightning<2.7,>=2
Requires-Dist: numpy<2.4,>=1.16.1
Requires-Dist: pandas<2.4,>=1.2
Requires-Dist: scanpy<1.12,>=1.9.5
Requires-Dist: scikit-learn<1.8,>=1.5.1
Requires-Dist: scipy<1.17,>=1.11.3
Requires-Dist: scvi-tools<1.4.1,>=1.0.4
Requires-Dist: session-info2
Requires-Dist: torch<2.10,>=2.1
